{"dependencies":[],"generated":{"js":"var MAX_ALLOC = Math.pow(2, 30) - 1 // default in iojs\nmodule.exports = function (iterations, keylen) {\n  if (typeof iterations !== 'number') {\n    throw new TypeError('Iterations not a number')\n  }\n\n  if (iterations < 0) {\n    throw new TypeError('Bad iterations')\n  }\n\n  if (typeof keylen !== 'number') {\n    throw new TypeError('Key length not a number')\n  }\n\n  if (keylen < 0 || keylen > MAX_ALLOC || keylen !== keylen) { /* eslint no-self-compare: 0 */\n    throw new TypeError('Bad key length')\n  }\n}\n","map":{"mappings":[{"source":"node_modules/pbkdf2/lib/precondition.js","original":{"line":1,"column":0},"generated":{"line":1,"column":0}},{"source":"node_modules/pbkdf2/lib/precondition.js","original":{"line":2,"column":0},"generated":{"line":2,"column":0}},{"source":"node_modules/pbkdf2/lib/precondition.js","original":{"line":3,"column":0},"generated":{"line":3,"column":0}},{"source":"node_modules/pbkdf2/lib/precondition.js","original":{"line":4,"column":0},"generated":{"line":4,"column":0}},{"source":"node_modules/pbkdf2/lib/precondition.js","original":{"line":5,"column":0},"generated":{"line":5,"column":0}},{"source":"node_modules/pbkdf2/lib/precondition.js","original":{"line":6,"column":0},"generated":{"line":6,"column":0}},{"source":"node_modules/pbkdf2/lib/precondition.js","original":{"line":7,"column":0},"generated":{"line":7,"column":0}},{"source":"node_modules/pbkdf2/lib/precondition.js","original":{"line":8,"column":0},"generated":{"line":8,"column":0}},{"source":"node_modules/pbkdf2/lib/precondition.js","original":{"line":9,"column":0},"generated":{"line":9,"column":0}},{"source":"node_modules/pbkdf2/lib/precondition.js","original":{"line":10,"column":0},"generated":{"line":10,"column":0}},{"source":"node_modules/pbkdf2/lib/precondition.js","original":{"line":11,"column":0},"generated":{"line":11,"column":0}},{"source":"node_modules/pbkdf2/lib/precondition.js","original":{"line":12,"column":0},"generated":{"line":12,"column":0}},{"source":"node_modules/pbkdf2/lib/precondition.js","original":{"line":13,"column":0},"generated":{"line":13,"column":0}},{"source":"node_modules/pbkdf2/lib/precondition.js","original":{"line":14,"column":0},"generated":{"line":14,"column":0}},{"source":"node_modules/pbkdf2/lib/precondition.js","original":{"line":15,"column":0},"generated":{"line":15,"column":0}},{"source":"node_modules/pbkdf2/lib/precondition.js","original":{"line":16,"column":0},"generated":{"line":16,"column":0}},{"source":"node_modules/pbkdf2/lib/precondition.js","original":{"line":17,"column":0},"generated":{"line":17,"column":0}},{"source":"node_modules/pbkdf2/lib/precondition.js","original":{"line":18,"column":0},"generated":{"line":18,"column":0}},{"source":"node_modules/pbkdf2/lib/precondition.js","original":{"line":19,"column":0},"generated":{"line":19,"column":0}}],"sources":{"node_modules/pbkdf2/lib/precondition.js":"var MAX_ALLOC = Math.pow(2, 30) - 1 // default in iojs\nmodule.exports = function (iterations, keylen) {\n  if (typeof iterations !== 'number') {\n    throw new TypeError('Iterations not a number')\n  }\n\n  if (iterations < 0) {\n    throw new TypeError('Bad iterations')\n  }\n\n  if (typeof keylen !== 'number') {\n    throw new TypeError('Key length not a number')\n  }\n\n  if (keylen < 0 || keylen > MAX_ALLOC || keylen !== keylen) { /* eslint no-self-compare: 0 */\n    throw new TypeError('Bad key length')\n  }\n}\n"},"lineCount":19}},"hash":"acf5673cdf491ca45d8827638771335d","cacheData":{"env":{}}}